{
  "type": "Program",
  "body": [
    {
      "type": "ExpressionStatement",
      "expression": {
        "type": "Literal",
        "value": "use strict",
        "raw": "'use strict'",
        "range": [
          119,
          131
        ],
        "loc": {
          "start": {
            "line": 9,
            "column": 0
          },
          "end": {
            "line": 9,
            "column": 12
          }
        }
      },
      "range": [
        119,
        132
      ],
      "loc": {
        "start": {
          "line": 9,
          "column": 0
        },
        "end": {
          "line": 9,
          "column": 13
        }
      },
      "leadingComments": [
        {
          "type": "Block",
          "value": "*\r\n *  Entrance of config\r\n *  Exports config modules\r\n *\r\n *  @author  Chip\r\n *  @date    January 6, 2015\r\n *\r\n ",
          "range": [
            0,
            117
          ],
          "loc": {
            "start": {
              "line": 1,
              "column": 0
            },
            "end": {
              "line": 8,
              "column": 3
            }
          }
        }
      ]
    },
    {
      "type": "ImportDeclaration",
      "specifiers": [
        {
          "type": "ImportDefaultSpecifier",
          "local": {
            "type": "Identifier",
            "name": "app",
            "range": [
              141,
              144
            ],
            "loc": {
              "start": {
                "line": 10,
                "column": 7
              },
              "end": {
                "line": 10,
                "column": 10
              }
            }
          },
          "range": [
            141,
            144
          ],
          "loc": {
            "start": {
              "line": 10,
              "column": 7
            },
            "end": {
              "line": 10,
              "column": 10
            }
          }
        }
      ],
      "source": {
        "type": "Literal",
        "value": "./AppConfig",
        "raw": "'./AppConfig'",
        "range": [
          150,
          163
        ],
        "loc": {
          "start": {
            "line": 10,
            "column": 16
          },
          "end": {
            "line": 10,
            "column": 29
          }
        }
      },
      "range": [
        134,
        164
      ],
      "loc": {
        "start": {
          "line": 10,
          "column": 0
        },
        "end": {
          "line": 10,
          "column": 30
        }
      }
    },
    {
      "type": "ImportDeclaration",
      "specifiers": [
        {
          "type": "ImportDefaultSpecifier",
          "local": {
            "type": "Identifier",
            "name": "notifier",
            "range": [
              173,
              181
            ],
            "loc": {
              "start": {
                "line": 11,
                "column": 7
              },
              "end": {
                "line": 11,
                "column": 15
              }
            }
          },
          "range": [
            173,
            181
          ],
          "loc": {
            "start": {
              "line": 11,
              "column": 7
            },
            "end": {
              "line": 11,
              "column": 15
            }
          }
        }
      ],
      "source": {
        "type": "Literal",
        "value": "./NotifierConfig",
        "raw": "'./NotifierConfig'",
        "range": [
          187,
          205
        ],
        "loc": {
          "start": {
            "line": 11,
            "column": 21
          },
          "end": {
            "line": 11,
            "column": 39
          }
        }
      },
      "range": [
        166,
        206
      ],
      "loc": {
        "start": {
          "line": 11,
          "column": 0
        },
        "end": {
          "line": 11,
          "column": 40
        }
      }
    },
    {
      "type": "ImportDeclaration",
      "specifiers": [
        {
          "type": "ImportDefaultSpecifier",
          "local": {
            "type": "Identifier",
            "name": "router",
            "range": [
              215,
              221
            ],
            "loc": {
              "start": {
                "line": 12,
                "column": 7
              },
              "end": {
                "line": 12,
                "column": 13
              }
            }
          },
          "range": [
            215,
            221
          ],
          "loc": {
            "start": {
              "line": 12,
              "column": 7
            },
            "end": {
              "line": 12,
              "column": 13
            }
          }
        }
      ],
      "source": {
        "type": "Literal",
        "value": "./RouterConfig",
        "raw": "'./RouterConfig'",
        "range": [
          227,
          243
        ],
        "loc": {
          "start": {
            "line": 12,
            "column": 19
          },
          "end": {
            "line": 12,
            "column": 35
          }
        }
      },
      "range": [
        208,
        244
      ],
      "loc": {
        "start": {
          "line": 12,
          "column": 0
        },
        "end": {
          "line": 12,
          "column": 36
        }
      }
    },
    {
      "type": "ImportDeclaration",
      "specifiers": [
        {
          "type": "ImportDefaultSpecifier",
          "local": {
            "type": "Identifier",
            "name": "sso",
            "range": [
              253,
              256
            ],
            "loc": {
              "start": {
                "line": 13,
                "column": 7
              },
              "end": {
                "line": 13,
                "column": 10
              }
            }
          },
          "range": [
            253,
            256
          ],
          "loc": {
            "start": {
              "line": 13,
              "column": 7
            },
            "end": {
              "line": 13,
              "column": 10
            }
          }
        }
      ],
      "source": {
        "type": "Literal",
        "value": "./SSOConfig",
        "raw": "'./SSOConfig'",
        "range": [
          262,
          275
        ],
        "loc": {
          "start": {
            "line": 13,
            "column": 16
          },
          "end": {
            "line": 13,
            "column": 29
          }
        }
      },
      "range": [
        246,
        276
      ],
      "loc": {
        "start": {
          "line": 13,
          "column": 0
        },
        "end": {
          "line": 13,
          "column": 30
        }
      }
    },
    {
      "type": "ExportDefaultDeclaration",
      "declaration": {
        "type": "ArrayExpression",
        "elements": [
          {
            "type": "Identifier",
            "name": "app",
            "range": [
              302,
              305
            ],
            "loc": {
              "start": {
                "line": 16,
                "column": 4
              },
              "end": {
                "line": 16,
                "column": 7
              }
            }
          },
          {
            "type": "Identifier",
            "name": "notifier",
            "range": [
              312,
              320
            ],
            "loc": {
              "start": {
                "line": 17,
                "column": 4
              },
              "end": {
                "line": 17,
                "column": 12
              }
            }
          },
          {
            "type": "Identifier",
            "name": "router",
            "range": [
              327,
              333
            ],
            "loc": {
              "start": {
                "line": 18,
                "column": 4
              },
              "end": {
                "line": 18,
                "column": 10
              }
            }
          },
          {
            "type": "Identifier",
            "name": "sso",
            "range": [
              340,
              343
            ],
            "loc": {
              "start": {
                "line": 19,
                "column": 4
              },
              "end": {
                "line": 19,
                "column": 7
              }
            }
          }
        ],
        "range": [
          295,
          346
        ],
        "loc": {
          "start": {
            "line": 15,
            "column": 15
          },
          "end": {
            "line": 20,
            "column": 1
          }
        },
        "leadingComments": [],
        "trailingComments": []
      },
      "range": [
        280,
        347
      ],
      "loc": {
        "start": {
          "line": 15,
          "column": 0
        },
        "end": {
          "line": 20,
          "column": 2
        }
      }
    }
  ],
  "sourceType": "module",
  "range": [
    119,
    347
  ],
  "loc": {
    "start": {
      "line": 9,
      "column": 0
    },
    "end": {
      "line": 20,
      "column": 2
    }
  },
  "comments": [
    {
      "type": "Block",
      "value": "*\r\n *  Entrance of config\r\n *  Exports config modules\r\n *\r\n *  @author  Chip\r\n *  @date    January 6, 2015\r\n *\r\n ",
      "range": [
        0,
        117
      ],
      "loc": {
        "start": {
          "line": 1,
          "column": 0
        },
        "end": {
          "line": 8,
          "column": 3
        }
      }
    }
  ]
}